.gitignore
.gitlab-ci.yml
AUTHORS
CMakeLists.txt
README.md
config.h.cmake
dune-fem-dg.pc.in
dune.module
pyproject.toml
setup.py
cmake/modules/CMakeLists.txt
cmake/modules/Codegen.cmake
cmake/modules/DuneFemDgMacros.cmake
cmake/modules/FindNETCDF.cmake
cmake/modules/TargetDistclean.cmake
cmake/scripts/RunGenerate.cmake
cmake/scripts/parameter.in
doc/CMakeLists.txt
doc/concept
doc/doxygen/CMakeLists.txt
doc/doxygen/Doxylocal
doc/doxygen/modules.txt
doc/doxygen/pages/advectiondiffusion.txt
doc/doxygen/pages/docrules.txt
doc/doxygen/pages/euler.txt
doc/doxygen/pages/examples.txt
doc/doxygen/pages/incompnavierstokes.txt
doc/doxygen/pages/mainpage.txt
doc/doxygen/pages/navierstokes.txt
doc/doxygen/pages/notation.txt
doc/doxygen/pages/parameters.txt
doc/doxygen/pages/poisson.txt
doc/doxygen/pages/problemstructure.txt
doc/doxygen/pages/stokes.txt
doc/pics/advectiondiffusion.png
doc/pics/algorithms_scheme.png
doc/pics/container1.png
doc/pics/container2.png
doc/pics/container3.png
doc/pics/container3_1.png
doc/pics/container3_2.png
doc/pics/container4.png
doc/pics/container5.png
doc/pics/container6.png
doc/pics/container7.png
doc/pics/euler.png
doc/pics/incompnavierstokes.png
doc/pics/local_eval_structure_.png
doc/pics/local_eval_structure_b.png
doc/pics/local_eval_structure_i.png
doc/pics/local_eval_structure_ib.png
doc/pics/local_eval_structure_q.png
doc/pics/local_eval_structure_qb.png
doc/pics/local_eval_structure_qi.png
doc/pics/local_eval_structure_qib.png
doc/pics/navierstokes.png
doc/pics/poisson.png
doc/pics/stokes.png
doc/pics/source/advectiondiffusion.svg
doc/pics/source/algorithms_scheme.svg
doc/pics/source/algorithms_scheme_base.svg
doc/pics/source/container1.svg
doc/pics/source/container2.svg
doc/pics/source/container3.svg
doc/pics/source/container3_1.svg
doc/pics/source/container3_2.svg
doc/pics/source/container4.svg
doc/pics/source/container5.svg
doc/pics/source/container6.svg
doc/pics/source/container7.svg
doc/pics/source/euler.svg
python/dune_fem_dg.egg-info/PKG-INFO
python/dune_fem_dg.egg-info/SOURCES.txt
python/dune_fem_dg.egg-info/dependency_links.txt
python/dune_fem_dg.egg-info/requires.txt
python/dune_fem_dg.egg-info/top_level.txt
