Metadata-Version: 2.1
Name: dune-fem-dg
Version: 2.11.0.2
Summary: The Dune FEM module: Discontinuous Galerkin for evolution equations
Home-page: https://www.dune-project.org/modules/dune-fem-dg/
Author: Andreas Dedner, Tobias Malkmus, Robert Kloefkorn, Stefan Wierling (geb. Girke)
Author-email: dune-fem@lists.dune-project.org
Classifier: Programming Language :: C++
Classifier: Programming Language :: Python :: 3
Classifier: License :: OSI Approved :: GNU General Public License (GPL)
Requires-Python: >=3.4
License-File: AUTHORS
